tap_octopus/__init__.py
tap_octopus/__main__.py
tap_octopus/client.py
tap_octopus/schemas/__init__.py
tap_octopus/streams.py
tap_octopus/tap.py
tap_octopus-0.0.2.dist-info/entry_points.txt
tap_octopus-0.0.2.dist-info/LICENSE
tap_octopus-0.0.2.dist-info/METADATA
tap_octopus-0.0.2.dist-info/WHEEL
tap_octopus-0.0.2.dist-info/RECORD
