Metadata-Version: 2.1
Name: tap-octopus
Version: 0.0.2
Summary: Singer tap for Octopus, built with the Meltano Singer SDK.
License: Apache-2.0
Keywords: ELT,Octopus
Author: damien harley
Author-email: damienkharley@gmail.com
Requires-Python: >=3.8
Classifier: Intended Audience :: Developers
Classifier: License :: OSI Approved :: Apache Software License
Classifier: Operating System :: OS Independent
Classifier: Programming Language :: Python :: 3
Classifier: Programming Language :: Python :: 3.8
Classifier: Programming Language :: Python :: 3.9
Classifier: Programming Language :: Python :: 3.10
Classifier: Programming Language :: Python :: 3.11
Classifier: Programming Language :: Python :: 3.12
Provides-Extra: s3
Requires-Dist: fs-s3fs (>=1.1.1,<1.2.0) ; extra == "s3"
Requires-Dist: importlib-resources (==6.4.*) ; python_version < "3.9"
Requires-Dist: requests (>=2.32.3,<2.33.0)
Requires-Dist: singer-sdk (>=0.39.1,<0.40.0)
